teamscritique/__init__.py
teamscritique/utils.py
teamscritique-0.2.dist-info/METADATA
teamscritique-0.2.dist-info/WHEEL
teamscritique-0.2.dist-info/top_level.txt
teamscritique-0.2.dist-info/RECORD
